{"assets/icons/github-round-icon.svg":["assets/icons/github-round-icon.svg"],"assets/icons/glyph-ov.svg":["assets/icons/glyph-ov.svg"],"assets/icons/linkedin-round-icon.svg":["assets/icons/linkedin-round-icon.svg"],"assets/icons/logo.svg":["assets/icons/logo.svg"],"assets/icons/twitter-round-icon.svg":["assets/icons/twitter-round-icon.svg"],"fonts/BlenderPro-Bold.ttf":["fonts/BlenderPro-Bold.ttf"],"fonts/BlenderPro-Medium.ttf":["fonts/BlenderPro-Medium.ttf"],"fonts/Futura-Book-Bold.ttf":["fonts/Futura-Book-Bold.ttf"],"fonts/Futura-Book-Regular.otf":["fonts/Futura-Book-Regular.otf"],"fonts/TT Interphases Pro Trial Bold.ttf":["fonts/TT Interphases Pro Trial Bold.ttf"],"fonts/TT Interphases Pro Trial Light.ttf":["fonts/TT Interphases Pro Trial Light.ttf"],"fonts/TT Interphases Pro Trial Medium.ttf":["fonts/TT Interphases Pro Trial Medium.ttf"],"fonts/tt-interfaces-mono-regular.ttf":["fonts/tt-interfaces-mono-regular.ttf"],"packages/cupertino_icons/assets/CupertinoIcons.ttf":["packages/cupertino_icons/assets/CupertinoIcons.ttf"]}